socket_for_humans/__init__.py
socket_for_humans/socket_for_humans.py
socket_for_humans-0.0.3.dist-info/METADATA
socket_for_humans-0.0.3.dist-info/WHEEL
socket_for_humans-0.0.3.dist-info/license.md
socket_for_humans-0.0.3.dist-info/top_level.txt
socket_for_humans-0.0.3.dist-info/RECORD
