Metadata-Version: 2.1
Name: socket-for-humans
Version: 0.0.3
Summary: A simplified TCP/IP socket setup suitable for many/most lightweight client server programs. The python standard library `socket` module has a relatively steep learning curve. The `socket_for_humans` module will help get most projects up and running quickly by wrapping the Python standard library socket module in an easy to use interface.
Home-page: https://gitlab.com/koyaanisqatsi.naqoyqatsi1/socket_for_humans
Author: koyaanisqatsi.naqoyqatsi@pm.me
Author-email: koyaanisqatsi.naqoyqatsi@pm.me
License: MIT
Keywords: networking,TCP/IP,simplified,client,server,socket
Platform: UNKNOWN
Classifier: Development Status :: 3 - Alpha
Classifier: Intended Audience :: Developers
Classifier: Topic :: System :: Networking
Classifier: License :: OSI Approved :: MIT License
Classifier: Programming Language :: Python :: 3
